{
  "inspections": [
    {
      "elementId": "67c5f0f6b5cbe8bb9a6b08a2f1e26608",
      "inspector": "FT",
      "status": "ok",
      "notes": "",
      "date": "2025-06-09",
      "lastModifiedBy": "user",
      "projectId": "default-project",
      "id": "insp_1749489773122_hqtge2dw7",
      "timestamp": "2025-06-09T17:22:55.170Z",
      "version": 2
    },
    {
      "elementId": "a75b5c017e8896a65396fd6bc88e6d1d",
      "inspector": "FT",
      "status": "issue",
      "notes": "",
      "date": "2025-06-09",
      "lastModifiedBy": "user",
      "projectId": "default-project",
      "id": "insp_1749489782161_2y4xpke0e",
      "timestamp": "2025-06-09T17:23:04.114Z",
      "version": 2
    },
    {
      "elementId": "09c2ea48bf73e981bed33ae0dd4f05ce",
      "inspector": "Mario",
      "status": "ok",
      "notes": "",
      "date": "2025-06-09",
      "lastModifiedBy": "user",
      "projectId": "default-project",
      "id": "insp_1749489793720_5xfbf5dol",
      "timestamp": "2025-06-09T17:23:15.659Z",
      "version": 2
    },
    {
      "elementId": "ef67f04731667c7aa0d6d86c480b610a",
      "inspector": "Mario",
      "status": "issue",
      "notes": "",
      "date": "2025-06-09",
      "lastModifiedBy": "user",
      "projectId": "default-project",
      "id": "insp_1749489799062_fhzh33v9k",
      "timestamp": "2025-06-10T11:59:10.720Z",
      "version": 4
    },
    {
      "elementId": "4eb93136d332c4d033ff4f9875ac512c",
      "inspector": "Gino",
      "status": "issue",
      "notes": "",
      "date": "2025-06-09",
      "lastModifiedBy": "user",
      "projectId": "default-project",
      "id": "insp_1749489854432_4664dls2g",
      "timestamp": "2025-06-09T17:24:16.752Z",
      "version": 2
    },
    {
      "elementId": "374186e798ed1addb84cb7129eeaaa25",
      "inspector": "SA",
      "status": "ok",
      "notes": "",
      "date": "2025-06-10",
      "lastModifiedBy": "user",
      "projectId": "default-project",
      "id": "insp_1749556763515_uo7g63ntc",
      "timestamp": "2025-06-10T11:59:25.672Z",
      "version": 2
    },
    {
      "elementId": "58c58b02a9cbacde8a70064550c351b8",
      "inspector": "VG",
      "status": "issue",
      "notes": "",
      "date": "2025-06-10",
      "lastModifiedBy": "user",
      "projectId": "default-project",
      "id": "insp_1749556772488_p9na3y32a",
      "timestamp": "2025-06-10T11:59:34.114Z",
      "version": 2
    },
    {
      "elementId": "dc92ae6ec66146305729534ef5dd6635",
      "inspector": "KL",
      "status": "issue",
      "notes": "",
      "date": "2025-06-10",
      "lastModifiedBy": "user",
      "projectId": "default-project",
      "id": "insp_1749558391266_bwkaj4hib",
      "timestamp": "2025-06-10T12:26:34.170Z",
      "version": 2
    },
    {
      "elementId": "67c5f0f6b5cbe8bb9a6b08a2f1e26608",
      "inspector": "FT",
      "status": "ok",
      "notes": "",
      "date": "2025-06-10",
      "lastModifiedBy": "user",
      "projectId": "123",
      "id": "insp_1749564984173_slqedvr8s",
      "timestamp": "2025-06-10T14:16:26.754Z",
      "version": 2
    },
    {
      "elementId": "ef67f04731667c7aa0d6d86c480b610a",
      "inspector": "MA",
      "status": "issue",
      "notes": "",
      "date": "2025-06-10",
      "lastModifiedBy": "user",
      "projectId": "123",
      "id": "insp_1749565023633_6af77qh96",
      "timestamp": "2025-06-10T14:17:06.139Z",
      "version": 2
    },
    {
      "elementId": "dc92ae6ec66146305729534ef5dd6635",
      "inspector": "RA",
      "status": "issue",
      "notes": "",
      "date": "2025-06-10",
      "lastModifiedBy": "user",
      "projectId": "123",
      "id": "insp_1749565031681_1anddi5li",
      "timestamp": "2025-06-10T14:17:14.819Z",
      "version": 3
    },
    {
      "elementId": "09c2ea48bf73e981bed33ae0dd4f05ce",
      "inspector": "FT",
      "status": "issue",
      "notes": "",
      "date": "2025-06-10",
      "lastModifiedBy": "user",
      "projectId": "123",
      "id": "insp_1749565039599_rxow0wjlp",
      "timestamp": "2025-06-10T14:17:21.210Z",
      "version": 2
    },
    {
      "elementId": "4eb93136d332c4d033ff4f9875ac512c",
      "inspector": "ED",
      "status": "issue",
      "notes": "",
      "date": "2025-06-10",
      "lastModifiedBy": "user",
      "projectId": "123",
      "id": "insp_1749565044317_vhtm5j14b",
      "timestamp": "2025-06-10T14:17:26.133Z",
      "version": 2
    },
    {
      "elementId": "977a504fcc18eb29a7d8060b161b5878",
      "inspector": "DF",
      "status": "issue",
      "notes": "",
      "date": "2025-06-10",
      "lastModifiedBy": "user",
      "projectId": "123",
      "id": "insp_1749565068953_p3vtytwbd",
      "timestamp": "2025-06-10T14:17:50.578Z",
      "version": 2
    },
    {
      "elementId": "59bbeaa8b7b39dedddd8ff4184ef6a34",
      "inspector": "FT",
      "status": "ok",
      "notes": "",
      "date": "2025-06-10",
      "lastModifiedBy": "user",
      "projectId": "123",
      "id": "insp_1749565081596_o7yk4b1bt",
      "timestamp": "2025-06-10T14:18:02.914Z",
      "version": 2
    },
    {
      "elementId": "860ccb1a97aa8cd24ba5dd173339e2d2",
      "inspector": "FT",
      "status": "ok",
      "notes": "",
      "date": "2025-06-10",
      "lastModifiedBy": "user",
      "projectId": "123",
      "id": "insp_1749565094403_qp1a3mezj",
      "timestamp": "2025-06-10T14:18:16.025Z",
      "version": 2
    },
    {
      "elementId": "27f9dcf29650937b9607515c88203eb0",
      "inspector": "FT",
      "status": "ok",
      "notes": "",
      "date": "2025-06-10",
      "lastModifiedBy": "user",
      "projectId": "proj_1749563662610_i6qqihs40",
      "id": "insp_1749565136477_e624uy62v",
      "timestamp": "2025-06-10T14:18:58.164Z",
      "version": 2
    },
    {
      "elementId": "a7d200b2b2fe30a45a94354bc3175ff1",
      "inspector": "FT",
      "status": "issue",
      "notes": "",
      "date": "2025-06-10",
      "lastModifiedBy": "user",
      "projectId": "proj_1749563662610_i6qqihs40",
      "id": "insp_1749565140613_n0d6cb7c9",
      "timestamp": "2025-06-10T14:19:01.886Z",
      "version": 2
    },
    {
      "elementId": "9cd2b321581870e97b12acdbf25f8896",
      "inspector": "FT",
      "status": "issue",
      "notes": "",
      "date": "2025-06-10",
      "lastModifiedBy": "user",
      "projectId": "proj_1749563662610_i6qqihs40",
      "id": "insp_1749565147769_9sritenn3",
      "timestamp": "2025-06-10T14:19:09.062Z",
      "version": 2
    },
    {
      "elementId": "746601e1e7a7f3a5381754d1c5e1d2bf",
      "inspector": "SD",
      "status": "issue",
      "notes": "",
      "date": "2025-06-10",
      "lastModifiedBy": "user",
      "projectId": "proj_1749563662610_i6qqihs40",
      "id": "insp_1749565158990_xbdqi6oac",
      "timestamp": "2025-06-10T14:19:20.850Z",
      "version": 2
    },
    {
      "elementId": "e590b83632211c1536480a93690ab3a0",
      "inspector": "ED",
      "status": "issue",
      "notes": "",
      "date": "2025-06-10",
      "lastModifiedBy": "user",
      "projectId": "proj_1749563662610_i6qqihs40",
      "id": "insp_1749565164088_lgwkm66fz",
      "timestamp": "2025-06-10T14:19:25.615Z",
      "version": 2
    },
    {
      "elementId": "af69c2c17476f465102a636bca2fb838",
      "inspector": "FT",
      "status": "ok",
      "notes": "",
      "date": "2025-06-10",
      "lastModifiedBy": "user",
      "projectId": "proj_1749563662610_i6qqihs40",
      "id": "insp_1749565169110_oskn1wmob",
      "timestamp": "2025-06-10T14:19:30.817Z",
      "version": 2
    },
    {
      "elementId": "a75b5c017e8896a65396fd6bc88e6d1d",
      "projectId": "123",
      "inspector": "FT",
      "status": "ok",
      "notes": "",
      "date": "2025-06-11",
      "lastModifiedBy": "user",
      "id": "insp_1749660310194_jbojmwynn",
      "timestamp": "2025-06-11T16:45:13.984Z",
      "version": 3
    }
  ],
  "projects": [],
  "users": [
    {
      "id": "default",
      "name": "Default User",
      "email": "user@example.com"
    }
  ],
  "metadata": {
    "version": "1.0.0",
    "lastBackup": "2025-06-09T17:18:33.282Z",
    "totalInspections": 0
  }
}